Metadata-Version: 2.1
Name: Lee-math
Version: 1.1
Summary: This is the first third-party library released by Cosmo Lee_math,a sophomore.
Home-page: https://github.com
Author: Cosmo Lee
License: UNKNOWN
Platform: UNKNOWN
